homework_checker/__init__.py
homework_checker/check_homework.py
homework_checker/print_repo_name.py
homework_checker/core/__init__.py
homework_checker/core/checker.py
homework_checker/core/md_writer.py
homework_checker/core/schema_manager.py
homework_checker/core/schema_tags.py
homework_checker/core/tasks.py
homework_checker/core/tools.py
homework_checker/core/tests/__init__.py
homework_checker/core/tests/test_checker.py
homework_checker/core/tests/test_task.py
homework_checker/core/tests/test_tools.py
homework_checker-2.0.0.dist-info/LICENCE.txt
homework_checker-2.0.0.dist-info/METADATA
homework_checker-2.0.0.dist-info/WHEEL
homework_checker-2.0.0.dist-info/entry_points.txt
homework_checker-2.0.0.dist-info/top_level.txt
homework_checker-2.0.0.dist-info/RECORD
