Metadata-Version: 2.1
Name: homework-checker
Version: 2.0.0
Summary: A generic homework checker.
Home-page: https://github.com/cpp-for-yourself/homework_checker
Download-URL: https://github.com/cpp-for-yourself/homework_checker/tarball/2.0.0
Author: Igor Bogoslavskyi
Author-email: igor.bogoslavskyi@gmail.com
Maintainer: Igor Bogoslavskyi
Maintainer-email: igor.bogoslavskyi@gmail.com
License: Apache 2.0
Keywords: homework-checker
Classifier: Environment :: Console
Classifier: Programming Language :: Python
Classifier: Intended Audience :: Developers
Classifier: License :: OSI Approved :: Apache Software License
License-File: LICENCE.txt
Requires-Dist: ruamel.yaml
Requires-Dist: schema
Requires-Dist: setuptools
Requires-Dist: cpplint
Requires-Dist: datetime
